app.py
git_smart_commit_ollama-0.1.0.dist-info/METADATA
git_smart_commit_ollama-0.1.0.dist-info/WHEEL
git_smart_commit_ollama-0.1.0.dist-info/entry_points.txt
git_smart_commit_ollama-0.1.0.dist-info/top_level.txt
git_smart_commit_ollama-0.1.0.dist-info/RECORD
