Metadata-Version: 2.4
Name: git-smart-commit-ollama
Version: 0.1.0
Summary: Generate concise Git commit messages using local LLMs via Ollama
Author: Saranya K
Author-email: your@email.com
Classifier: Programming Language :: Python :: 3
Classifier: License :: OSI Approved :: MIT License
Requires-Python: >=3.7
Dynamic: author
Dynamic: author-email
Dynamic: classifier
Dynamic: description
Dynamic: description-content-type
Dynamic: requires-python
Dynamic: summary
